allocloud/openapt/__init__.py
allocloud/openapt/__main__.py
allocloud/openapt/commands.py
allocloud/openapt/dependency.py
allocloud/openapt/errors.py
allocloud/openapt/logging.py
allocloud/openapt/models.py
allocloud/openapt/specs/__init__.py
allocloud/openapt/specs/openapt-specs_1.0.json
tests/test_e2e.py
tests/e2e/__init__.py
openapt-1.0.0.dist-info/LICENSE
openapt-1.0.0.dist-info/METADATA
openapt-1.0.0.dist-info/WHEEL
openapt-1.0.0.dist-info/entry_points.txt
openapt-1.0.0.dist-info/top_level.txt
openapt-1.0.0.dist-info/RECORD
