Metadata-Version: 2.1
Name: openapt
Version: 1.0.0
Summary: Specify and automate APT repository management.
Home-page: UNKNOWN
Author: Raphael Medaer
Author-email: raphael.medaer@allocloud.com
License: UNKNOWN
Platform: UNKNOWN
Classifier: Programming Language :: Python :: 3.7
Requires-Python: >=3.7
Requires-Dist: jsonschema
Requires-Dist: pyyaml
